quantready/__init__.py
quantready/__main__.py
quantready/cli.py
quantready/config.py
quantready/helpers.py
quantready/initialize.py
quantready/models.py
quantready-0.2.0.dist-info/LICENSE
quantready-0.2.0.dist-info/METADATA
quantready-0.2.0.dist-info/WHEEL
quantready-0.2.0.dist-info/entry_points.txt
quantready-0.2.0.dist-info/RECORD
