Metadata-Version: 2.1
Name: quantready
Version: 0.2.0
Summary: A CLI to quickly launch data-driven and API-first businesses - using the modern python stack
License: MIT
Author: Sean Kruzel
Author-email: sean@closedloop.tech
Requires-Python: >=3.10,<4.0
Classifier: License :: OSI Approved :: MIT License
Classifier: Operating System :: OS Independent
Classifier: Programming Language :: Python :: 3
Classifier: Programming Language :: Python :: 3.10
Classifier: Programming Language :: Python :: 3.11
Classifier: Programming Language :: Python :: 3.10
Classifier: Topic :: Software Development :: Libraries :: Python Modules
Requires-Dist: colorama (>=0.4.6,<0.5.0)
Requires-Dist: gcloud (>=0.18.3,<0.19.0)
Requires-Dist: pre-commit (>=3.3.1,<4.0.0)
Requires-Dist: pydantic (>=1.10.7,<2.0.0)
Requires-Dist: pyfiglet (>=0.8.post1,<0.9)
Requires-Dist: python-dotenv (>=1.0.0,<2.0.0)
Requires-Dist: tabulate (>=0.9.0,<0.10.0)
Requires-Dist: termcolor (>=2.3.0,<3.0.0)
Requires-Dist: twine (>=4.0.2,<5.0.0)
Requires-Dist: typer (>=0.9.0,<0.10.0)
Project-URL: Bug Tracker, https://github.com/closedloop-technologies/quantready/issues
Project-URL: Repository, https://github.com/closedloop-technologies/quantready
